client/__init__.py
client/api_sender.py
client/bound_instruction_chain.py
client/instruction_builder.py
client/instruction_chain.py
client/enums/__init__.py
client/enums/action_type.py
client/enums/block_type.py
client/enums/content_type.py
client/enums/element_type.py
client/enums/identificator_type.py
client/models/__init__.py
client/models/api_result.py
client/models/driver_options.py
client/util/__init__.py
client/util/exceptions.py
web_scraper_client-0.2.0.dist-info/licenses/LICENSE
web_scraper_client-0.2.0.dist-info/METADATA
web_scraper_client-0.2.0.dist-info/WHEEL
web_scraper_client-0.2.0.dist-info/top_level.txt
web_scraper_client-0.2.0.dist-info/RECORD
