Metadata-Version: 2.4
Name: web-scraper-client
Version: 0.2.0
Summary: Client library for https://github.com/snackbeard/web-scraper-api
Author: Snackbeard
License: MIT License
Project-URL: Homepage, https://github.com/snackbeard/web-scraper-api
Project-URL: Repository, https://github.com/snackbeard/web-scraper-api
License-File: LICENSE
Requires-Dist: requests
Dynamic: license-file
